config/__init__.py
config/commands.py
config/config_loader.py
config/manager.py
config/plugin.py
openstack_config-1.0.2.dist-info/METADATA
openstack_config-1.0.2.dist-info/WHEEL
openstack_config-1.0.2.dist-info/entry_points.txt
openstack_config-1.0.2.dist-info/top_level.txt
openstack_config-1.0.2.dist-info/RECORD
