Metadata-Version: 2.1
Name: openstack-config
Version: 1.0.2
Summary: Openstack client extension that add kubectl-like config and context management
Classifier: Environment :: OpenStack
Classifier: Intended Audience :: Information Technology
Classifier: Intended Audience :: System Administrators
Classifier: License :: OSI Approved :: Apache Software License
Classifier: Operating System :: POSIX :: Linux
Classifier: Programming Language :: Python
Classifier: Programming Language :: Python :: Implementation :: CPython
Classifier: Programming Language :: Python :: 3 :: Only
Classifier: Programming Language :: Python :: 3
Classifier: Programming Language :: Python :: 3.8
Classifier: Programming Language :: Python :: 3.9
Classifier: Programming Language :: Python :: 3.10
Classifier: Programming Language :: Python :: 3.11
Requires-Python: >=3.8
Requires-Dist: pbr>=6.1.0
Requires-Dist: osc-lib>=3.2.0
Requires-Dist: platformdirs>=4.3.6
Requires-Dist: ruamel.yaml>=0.18.10
Requires-Dist: glom>=24.11.0
Requires-Dist: python-openstackclient>=7.2.1
Requires-Dist: requests>=2.32.3
Provides-Extra: cli
Requires-Dist: python-openstackclient>=3.12.0; extra == "cli"
